overlay_lib/__init__.py
overlay_lib/classes.py
overlay_lib/overlay.py
PythonOverlayLib-1.2.dist-info/LICENSE
PythonOverlayLib-1.2.dist-info/METADATA
PythonOverlayLib-1.2.dist-info/WHEEL
PythonOverlayLib-1.2.dist-info/top_level.txt
PythonOverlayLib-1.2.dist-info/RECORD
