Metadata-Version: 2.1
Name: PythonOverlayLib
Version: 1.2
Summary: Python library designed to create customizable overlays for desktop applications. It uses PyQt5 to draw shapes such as circles, rectangles, and lines on a transparent window that stays on top of other windows.
Home-page: https://github.com/LUXTACO/PythonOverlayLib
Author: Takkeshi
Author-email: tacomastabusiness@gmail.com
Maintainer: Takkeshi, akazdayo
License-File: LICENSE
Requires-Dist: PyQt5 >=5.15.4
